django_admin_rangefilter_jalali-0.4.3.0.dist-info/DESCRIPTION.rst
django_admin_rangefilter_jalali-0.4.3.0.dist-info/METADATA
django_admin_rangefilter_jalali-0.4.3.0.dist-info/RECORD
django_admin_rangefilter_jalali-0.4.3.0.dist-info/WHEEL
django_admin_rangefilter_jalali-0.4.3.0.dist-info/metadata.json
django_admin_rangefilter_jalali-0.4.3.0.dist-info/top_level.txt
rangefilter_jalali/__init__.py
rangefilter_jalali/apps.py
rangefilter_jalali/filter.py
rangefilter_jalali/models.py
rangefilter_jalali/tests.py
rangefilter_jalali/templates/rangefilter/date_filter.html
rangefilter_jalali/templates/rangefilter/date_filter_1_8.html
rangefilter_jalali/templatetags/__init__.py
rangefilter_jalali/templatetags/rangefilter_compat.py
